odoo10_addon_stock_picking_delivery_rate-10.0.1.0.0-py2.7-nspkg.pth
odoo/addons/stock_picking_delivery_rate/README.rst
odoo/addons/stock_picking_delivery_rate/__init__.py
odoo/addons/stock_picking_delivery_rate/__manifest__.py
odoo/addons/stock_picking_delivery_rate/models/__init__.py
odoo/addons/stock_picking_delivery_rate/models/delivery_carrier.py
odoo/addons/stock_picking_delivery_rate/models/stock_picking.py
odoo/addons/stock_picking_delivery_rate/models/stock_picking_rate.py
odoo/addons/stock_picking_delivery_rate/security/ir.model.access.csv
odoo/addons/stock_picking_delivery_rate/static/description/icon.png
odoo/addons/stock_picking_delivery_rate/tests/__init__.py
odoo/addons/stock_picking_delivery_rate/tests/common.py
odoo/addons/stock_picking_delivery_rate/tests/test_stock_picking_rate.py
odoo/addons/stock_picking_delivery_rate/tests/test_stock_picking_rate_purchase.py
odoo/addons/stock_picking_delivery_rate/views/delivery_carrier_view.xml
odoo/addons/stock_picking_delivery_rate/views/stock_picking_rate_view.xml
odoo/addons/stock_picking_delivery_rate/views/stock_picking_view.xml
odoo/addons/stock_picking_delivery_rate/wizards/__init__.py
odoo/addons/stock_picking_delivery_rate/wizards/stock_picking_rate_purchase.py
odoo/addons/stock_picking_delivery_rate/wizards/stock_picking_rate_purchase_view.xml
odoo10_addon_stock_picking_delivery_rate-10.0.1.0.0.dist-info/DESCRIPTION.rst
odoo10_addon_stock_picking_delivery_rate-10.0.1.0.0.dist-info/METADATA
odoo10_addon_stock_picking_delivery_rate-10.0.1.0.0.dist-info/RECORD
odoo10_addon_stock_picking_delivery_rate-10.0.1.0.0.dist-info/WHEEL
odoo10_addon_stock_picking_delivery_rate-10.0.1.0.0.dist-info/metadata.json
odoo10_addon_stock_picking_delivery_rate-10.0.1.0.0.dist-info/namespace_packages.txt
odoo10_addon_stock_picking_delivery_rate-10.0.1.0.0.dist-info/top_level.txt
